rendermd/__init__.py
rendermd/__init__.pyi
rendermd/command_line.py
rendermd/command_line.pyi
rendermd/command_parser.py
rendermd/command_parser.pyi
rendermd/core.py
rendermd/core.pyi
rendermd/printer.py
rendermd/printer.pyi
rendermd/py.typed
rendermd/shell.py
rendermd/shell.pyi
rendermd/toc.py
rendermd/toc.pyi
rendermd-0.6.1.dist-info/LICENSE
rendermd-0.6.1.dist-info/METADATA
rendermd-0.6.1.dist-info/WHEEL
rendermd-0.6.1.dist-info/entry_points.txt
rendermd-0.6.1.dist-info/top_level.txt
rendermd-0.6.1.dist-info/RECORD
