Metadata-Version: 2.1
Name: rendermd
Version: 0.6.1
Summary: Python type code generator
Home-page: https://github.com/conanfanli/rendermd
Author: Conan Li
Author-email: conanlics@gmail.com
License: MIT
Keywords: Python,TypeScript,Dataclass,Code Generation
Platform: UNKNOWN
Classifier: Development Status :: 3 - Alpha
Classifier: License :: OSI Approved :: MIT License
Classifier: Programming Language :: Python :: 3.8
Requires-Python: ~=3.11
Requires-Dist: md-toc
Provides-Extra: dev
Requires-Dist: ipython; extra == "dev"
Requires-Dist: mypy; extra == "dev"
